{
  "type": "File",
  "start": 0,
  "end": 300,
  "loc": {
    "start": {
      "line": 1,
      "column": 0
    },
    "end": {
      "line": 16,
      "column": 0
    }
  },
  "program": {
    "type": "Program",
    "start": 0,
    "end": 300,
    "loc": {
      "start": {
        "line": 1,
        "column": 0
      },
      "end": {
        "line": 16,
        "column": 0
      }
    },
    "sourceType": "module",
    "body": [
      {
        "type": "Identifier",
        "start": 0,
        "end": 269,
        "loc": {
          "start": {
            "line": 1,
            "column": 0
          },
          "end": {
            "line": 13,
            "column": 1
          }
        },
        "declarations": [
          {
            "type": "VariableDeclarator",
            "start": 6,
            "end": 269,
            "loc": {
              "start": {
                "line": 1,
                "column": 6
              },
              "end": {
                "line": 13,
                "column": 1
              }
            },
            "id": {
              "type": "Identifier",
              "start": 6,
              "end": 19,
              "loc": {
                "start": {
                  "line": 1,
                  "column": 6
                },
                "end": {
                  "line": 1,
                  "column": 19
                },
                "identifierName": "unimplemented"
              },
              "name": "unimplemented"
            },
            "init": {
              "type": "ObjectExpression",
              "start": 22,
              "end": 269,
              "loc": {
                "start": {
                  "line": 1,
                  "column": 22
                },
                "end": {
                  "line": 13,
                  "column": 1
                }
              },
              "properties": [
                {
                  "type": "ObjectMethod",
                  "start": 26,
                  "end": 267,
                  "loc": {
                    "start": {
                      "line": 2,
                      "column": 2
                    },
                    "end": {
                      "line": 12,
                      "column": 3
                    }
                  },
                  "method": true,
                  "shorthand": false,
                  "computed": false,
                  "key": {
                    "type": "Identifier",
                    "start": 26,
                    "end": 32,
                    "loc": {
                      "start": {
                        "line": 2,
                        "column": 2
                      },
                      "end": {
                        "line": 2,
                        "column": 8
                      },
                      "identifierName": "create"
                    },
                    "name": "create"
                  },
                  "kind": "method",
                  "id": null,
                  "generator": false,
                  "expression": false,
                  "async": false,
                  "params": [
                    {
                      "type": "Identifier",
                      "start": 34,
                      "end": 48,
                      "loc": {
                        "start": {
                          "line": 2,
                          "column": 10
                        },
                        "end": {
                          "line": 2,
                          "column": 24
                        },
                        "identifierName": "runtimeOptions"
                      },
                      "name": "runtimeOptions"
                    }
                  ],
                  "body": {
                    "type": "BlockStatement",
                    "start": 50,
                    "end": 267,
                    "loc": {
                      "start": {
                        "line": 2,
                        "column": 26
                      },
                      "end": {
                        "line": 12,
                        "column": 3
                      }
                    },
                    "body": [
                      {
                        "type": "IfStatement",
                        "start": 56,
                        "end": 116,
                        "loc": {
                          "start": {
                            "line": 3,
                            "column": 4
                          },
                          "end": {
                            "line": 5,
                            "column": 5
                          }
                        },
                        "test": {
                          "type": "UnaryExpression",
                          "start": 60,
                          "end": 84,
                          "loc": {
                            "start": {
                              "line": 3,
                              "column": 8
                            },
                            "end": {
                              "line": 3,
                              "column": 32
                            }
                          },
                          "operator": "!",
                          "prefix": true,
                          "argument": {
                            "type": "MemberExpression",
                            "start": 61,
                            "end": 84,
                            "loc": {
                              "start": {
                                "line": 3,
                                "column": 9
                              },
                              "end": {
                                "line": 3,
                                "column": 32
                              }
                            },
                            "object": {
                              "type": "Identifier",
                              "start": 61,
                              "end": 75,
                              "loc": {
                                "start": {
                                  "line": 3,
                                  "column": 9
                                },
                                "end": {
                                  "line": 3,
                                  "column": 23
                                },
                                "identifierName": "runtimeOptions"
                              },
                              "name": "runtimeOptions"
                            },
                            "property": {
                              "type": "Identifier",
                              "start": 76,
                              "end": 84,
                              "loc": {
                                "start": {
                                  "line": 3,
                                  "column": 24
                                },
                                "end": {
                                  "line": 3,
                                  "column": 32
                                },
                                "identifierName": "useAudio"
                              },
                              "name": "useAudio"
                            },
                            "computed": false
                          },
                          "extra": {
                            "parenthesizedArgument": false
                          }
                        },
                        "consequent": {
                          "type": "BlockStatement",
                          "start": 86,
                          "end": 116,
                          "loc": {
                            "start": {
                              "line": 3,
                              "column": 34
                            },
                            "end": {
                              "line": 5,
                              "column": 5
                            }
                          },
                          "body": [
                            {
                              "type": "ReturnStatement",
                              "start": 94,
                              "end": 110,
                              "loc": {
                                "start": {
                                  "line": 4,
                                  "column": 6
                                },
                                "end": {
                                  "line": 4,
                                  "column": 22
                                }
                              },
                              "argument": {
                                "type": "Identifier",
                                "start": 101,
                                "end": 110,
                                "loc": {
                                  "start": {
                                    "line": 4,
                                    "column": 13
                                  },
                                  "end": {
                                    "line": 4,
                                    "column": 22
                                  },
                                  "identifierName": "undefined"
                                },
                                "name": "undefined"
                              }
                            }
                          ],
                          "directives": []
                        },
                        "alternate": null
                      },
                      {
                        "type": "VariableDeclaration",
                        "start": 122,
                        "end": 245,
                        "loc": {
                          "start": {
                            "line": 7,
                            "column": 4
                          },
                          "end": {
                            "line": 9,
                            "column": 5
                          }
                        },
                        "declarations": [
                          {
                            "type": "VariableDeclarator",
                            "start": 128,
                            "end": 245,
                            "loc": {
                              "start": {
                                "line": 7,
                                "column": 10
                              },
                              "end": {
                                "line": 9,
                                "column": 5
                              }
                            },
                            "id": {
                              "type": "Identifier",
                              "start": 128,
                              "end": 133,
                              "loc": {
                                "start": {
                                  "line": 7,
                                  "column": 10
                                },
                                "end": {
                                  "line": 7,
                                  "column": 15
                                },
                                "identifierName": "audio"
                              },
                              "name": "audio"
                            },
                            "init": {
                              "type": "ObjectExpression",
                              "start": 136,
                              "end": 245,
                              "loc": {
                                "start": {
                                  "line": 7,
                                  "column": 18
                                },
                                "end": {
                                  "line": 9,
                                  "column": 5
                                }
                              },
                              "properties": [
                                {
                                  "type": "ObjectProperty",
                                  "start": 144,
                                  "end": 239,
                                  "loc": {
                                    "start": {
                                      "line": 8,
                                      "column": 6
                                    },
                                    "end": {
                                      "line": 8,
                                      "column": 101
                                    }
                                  },
                                  "method": false,
                                  "shorthand": false,
                                  "computed": false,
                                  "key": {
                                    "type": "Identifier",
                                    "start": 144,
                                    "end": 149,
                                    "loc": {
                                      "start": {
                                        "line": 8,
                                        "column": 6
                                      },
                                      "end": {
                                        "line": 8,
                                        "column": 11
                                      },
                                      "identifierName": "error"
                                    },
                                    "name": "error"
                                  },
                                  "value": {
                                    "type": "StringLiteral",
                                    "start": 151,
                                    "end": 239,
                                    "loc": {
                                      "start": {
                                        "line": 8,
                                        "column": 13
                                      },
                                      "end": {
                                        "line": 8,
                                        "column": 101
                                      }
                                    },
                                    "extra": {
                                      "rawValue": "Sorry, the Audio Manager is not yet implemented! set useAudio runtime option to false!",
                                      "raw": "'Sorry, the Audio Manager is not yet implemented! set useAudio runtime option to false!'"
                                    },
                                    "value": "Sorry, the Audio Manager is not yet implemented! set useAudio runtime option to false!"
                                  }
                                }
                              ]
                            }
                          }
                        ],
                        "kind": "const"
                      },
                      {
                        "type": "ReturnStatement",
                        "start": 251,
                        "end": 263,
                        "loc": {
                          "start": {
                            "line": 11,
                            "column": 4
                          },
                          "end": {
                            "line": 11,
                            "column": 16
                          }
                        },
                        "argument": {
                          "type": "Identifier",
                          "start": 258,
                          "end": 263,
                          "loc": {
                            "start": {
                              "line": 11,
                              "column": 11
                            },
                            "end": {
                              "line": 11,
                              "column": 16
                            },
                            "identifierName": "audio"
                          },
                          "name": "audio"
                        }
                      }
                    ],
                    "directives": []
                  }
                }
              ]
            }
          }
        ],
        "kind": "const",
        "name": "_",
        "leadingComments": [],
        "trailingComments": []
      },
      {
        "type": "Identifier",
        "start": 271,
        "end": 299,
        "loc": {
          "start": {
            "line": 15,
            "column": 0
          },
          "end": {
            "line": 15,
            "column": 28
          }
        },
        "declaration": {
          "type": "Identifier",
          "start": 286,
          "end": 299,
          "loc": {
            "start": {
              "line": 15,
              "column": 15
            },
            "end": {
              "line": 15,
              "column": 28
            },
            "identifierName": "unimplemented"
          },
          "name": "unimplemented"
        },
        "name": "_",
        "leadingComments": [],
        "trailingComments": []
      },
      {
        "type": "ExportDefaultDeclaration",
        "start": 271,
        "end": 299,
        "loc": {
          "start": {
            "line": 15,
            "column": 0
          },
          "end": {
            "line": 15,
            "column": 28
          }
        },
        "declaration": {
          "type": "VariableDeclaration",
          "start": 0,
          "end": 269,
          "loc": {
            "start": {
              "line": 1,
              "column": 0
            },
            "end": {
              "line": 13,
              "column": 1
            }
          },
          "declarations": [
            {
              "type": "VariableDeclarator",
              "start": 6,
              "end": 269,
              "loc": {
                "start": {
                  "line": 1,
                  "column": 6
                },
                "end": {
                  "line": 13,
                  "column": 1
                }
              },
              "id": {
                "type": "Identifier",
                "start": 6,
                "end": 19,
                "loc": {
                  "start": {
                    "line": 1,
                    "column": 6
                  },
                  "end": {
                    "line": 1,
                    "column": 19
                  },
                  "identifierName": "unimplemented"
                },
                "name": "unimplemented"
              },
              "init": {
                "type": "ObjectExpression",
                "start": 22,
                "end": 269,
                "loc": {
                  "start": {
                    "line": 1,
                    "column": 22
                  },
                  "end": {
                    "line": 13,
                    "column": 1
                  }
                },
                "properties": [
                  {
                    "type": "ObjectMethod",
                    "start": 26,
                    "end": 267,
                    "loc": {
                      "start": {
                        "line": 2,
                        "column": 2
                      },
                      "end": {
                        "line": 12,
                        "column": 3
                      }
                    },
                    "method": true,
                    "shorthand": false,
                    "computed": false,
                    "key": {
                      "type": "Identifier",
                      "start": 26,
                      "end": 32,
                      "loc": {
                        "start": {
                          "line": 2,
                          "column": 2
                        },
                        "end": {
                          "line": 2,
                          "column": 8
                        },
                        "identifierName": "create"
                      },
                      "name": "create"
                    },
                    "kind": "method",
                    "id": null,
                    "generator": false,
                    "expression": false,
                    "async": false,
                    "params": [
                      {
                        "type": "Identifier",
                        "start": 34,
                        "end": 48,
                        "loc": {
                          "start": {
                            "line": 2,
                            "column": 10
                          },
                          "end": {
                            "line": 2,
                            "column": 24
                          },
                          "identifierName": "runtimeOptions"
                        },
                        "name": "runtimeOptions"
                      }
                    ],
                    "body": {
                      "type": "BlockStatement",
                      "start": 50,
                      "end": 267,
                      "loc": {
                        "start": {
                          "line": 2,
                          "column": 26
                        },
                        "end": {
                          "line": 12,
                          "column": 3
                        }
                      },
                      "body": [
                        {
                          "type": "IfStatement",
                          "start": 56,
                          "end": 116,
                          "loc": {
                            "start": {
                              "line": 3,
                              "column": 4
                            },
                            "end": {
                              "line": 5,
                              "column": 5
                            }
                          },
                          "test": {
                            "type": "UnaryExpression",
                            "start": 60,
                            "end": 84,
                            "loc": {
                              "start": {
                                "line": 3,
                                "column": 8
                              },
                              "end": {
                                "line": 3,
                                "column": 32
                              }
                            },
                            "operator": "!",
                            "prefix": true,
                            "argument": {
                              "type": "MemberExpression",
                              "start": 61,
                              "end": 84,
                              "loc": {
                                "start": {
                                  "line": 3,
                                  "column": 9
                                },
                                "end": {
                                  "line": 3,
                                  "column": 32
                                }
                              },
                              "object": {
                                "type": "Identifier",
                                "start": 61,
                                "end": 75,
                                "loc": {
                                  "start": {
                                    "line": 3,
                                    "column": 9
                                  },
                                  "end": {
                                    "line": 3,
                                    "column": 23
                                  },
                                  "identifierName": "runtimeOptions"
                                },
                                "name": "runtimeOptions"
                              },
                              "property": {
                                "type": "Identifier",
                                "start": 76,
                                "end": 84,
                                "loc": {
                                  "start": {
                                    "line": 3,
                                    "column": 24
                                  },
                                  "end": {
                                    "line": 3,
                                    "column": 32
                                  },
                                  "identifierName": "useAudio"
                                },
                                "name": "useAudio"
                              },
                              "computed": false
                            },
                            "extra": {
                              "parenthesizedArgument": false
                            }
                          },
                          "consequent": {
                            "type": "BlockStatement",
                            "start": 86,
                            "end": 116,
                            "loc": {
                              "start": {
                                "line": 3,
                                "column": 34
                              },
                              "end": {
                                "line": 5,
                                "column": 5
                              }
                            },
                            "body": [
                              {
                                "type": "ReturnStatement",
                                "start": 94,
                                "end": 110,
                                "loc": {
                                  "start": {
                                    "line": 4,
                                    "column": 6
                                  },
                                  "end": {
                                    "line": 4,
                                    "column": 22
                                  }
                                },
                                "argument": {
                                  "type": "Identifier",
                                  "start": 101,
                                  "end": 110,
                                  "loc": {
                                    "start": {
                                      "line": 4,
                                      "column": 13
                                    },
                                    "end": {
                                      "line": 4,
                                      "column": 22
                                    },
                                    "identifierName": "undefined"
                                  },
                                  "name": "undefined"
                                }
                              }
                            ],
                            "directives": []
                          },
                          "alternate": null
                        },
                        {
                          "type": "VariableDeclaration",
                          "start": 122,
                          "end": 245,
                          "loc": {
                            "start": {
                              "line": 7,
                              "column": 4
                            },
                            "end": {
                              "line": 9,
                              "column": 5
                            }
                          },
                          "declarations": [
                            {
                              "type": "VariableDeclarator",
                              "start": 128,
                              "end": 245,
                              "loc": {
                                "start": {
                                  "line": 7,
                                  "column": 10
                                },
                                "end": {
                                  "line": 9,
                                  "column": 5
                                }
                              },
                              "id": {
                                "type": "Identifier",
                                "start": 128,
                                "end": 133,
                                "loc": {
                                  "start": {
                                    "line": 7,
                                    "column": 10
                                  },
                                  "end": {
                                    "line": 7,
                                    "column": 15
                                  },
                                  "identifierName": "audio"
                                },
                                "name": "audio"
                              },
                              "init": {
                                "type": "ObjectExpression",
                                "start": 136,
                                "end": 245,
                                "loc": {
                                  "start": {
                                    "line": 7,
                                    "column": 18
                                  },
                                  "end": {
                                    "line": 9,
                                    "column": 5
                                  }
                                },
                                "properties": [
                                  {
                                    "type": "ObjectProperty",
                                    "start": 144,
                                    "end": 239,
                                    "loc": {
                                      "start": {
                                        "line": 8,
                                        "column": 6
                                      },
                                      "end": {
                                        "line": 8,
                                        "column": 101
                                      }
                                    },
                                    "method": false,
                                    "shorthand": false,
                                    "computed": false,
                                    "key": {
                                      "type": "Identifier",
                                      "start": 144,
                                      "end": 149,
                                      "loc": {
                                        "start": {
                                          "line": 8,
                                          "column": 6
                                        },
                                        "end": {
                                          "line": 8,
                                          "column": 11
                                        },
                                        "identifierName": "error"
                                      },
                                      "name": "error"
                                    },
                                    "value": {
                                      "type": "StringLiteral",
                                      "start": 151,
                                      "end": 239,
                                      "loc": {
                                        "start": {
                                          "line": 8,
                                          "column": 13
                                        },
                                        "end": {
                                          "line": 8,
                                          "column": 101
                                        }
                                      },
                                      "extra": {
                                        "rawValue": "Sorry, the Audio Manager is not yet implemented! set useAudio runtime option to false!",
                                        "raw": "'Sorry, the Audio Manager is not yet implemented! set useAudio runtime option to false!'"
                                      },
                                      "value": "Sorry, the Audio Manager is not yet implemented! set useAudio runtime option to false!"
                                    }
                                  }
                                ]
                              }
                            }
                          ],
                          "kind": "const"
                        },
                        {
                          "type": "ReturnStatement",
                          "start": 251,
                          "end": 263,
                          "loc": {
                            "start": {
                              "line": 11,
                              "column": 4
                            },
                            "end": {
                              "line": 11,
                              "column": 16
                            }
                          },
                          "argument": {
                            "type": "Identifier",
                            "start": 258,
                            "end": 263,
                            "loc": {
                              "start": {
                                "line": 11,
                                "column": 11
                              },
                              "end": {
                                "line": 11,
                                "column": 16
                              },
                              "identifierName": "audio"
                            },
                            "name": "audio"
                          }
                        }
                      ],
                      "directives": []
                    }
                  }
                ]
              }
            }
          ],
          "kind": "const",
          "leadingComments": [],
          "trailingComments": []
        }
      }
    ],
    "directives": []
  },
  "comments": [],
  "tokens": [
    {
      "type": {
        "label": "const",
        "keyword": "const",
        "beforeExpr": false,
        "startsExpr": false,
        "rightAssociative": false,
        "isLoop": false,
        "isAssign": false,
        "prefix": false,
        "postfix": false,
        "binop": null,
        "updateContext": null
      },
      "value": "const",
      "start": 0,
      "end": 5,
      "loc": {
        "start": {
          "line": 1,
          "column": 0
        },
        "end": {
          "line": 1,
          "column": 5
        }
      }
    },
    {
      "type": {
        "label": "name",
        "beforeExpr": false,
        "startsExpr": true,
        "rightAssociative": false,
        "isLoop": false,
        "isAssign": false,
        "prefix": false,
        "postfix": false,
        "binop": null
      },
      "value": "unimplemented",
      "start": 6,
      "end": 19,
      "loc": {
        "start": {
          "line": 1,
          "column": 6
        },
        "end": {
          "line": 1,
          "column": 19
        }
      }
    },
    {
      "type": {
        "label": "=",
        "beforeExpr": true,
        "startsExpr": false,
        "rightAssociative": false,
        "isLoop": false,
        "isAssign": true,
        "prefix": false,
        "postfix": false,
        "binop": null,
        "updateContext": null
      },
      "value": "=",
      "start": 20,
      "end": 21,
      "loc": {
        "start": {
          "line": 1,
          "column": 20
        },
        "end": {
          "line": 1,
          "column": 21
        }
      }
    },
    {
      "type": {
        "label": "{",
        "beforeExpr": true,
        "startsExpr": true,
        "rightAssociative": false,
        "isLoop": false,
        "isAssign": false,
        "prefix": false,
        "postfix": false,
        "binop": null
      },
      "start": 22,
      "end": 23,
      "loc": {
        "start": {
          "line": 1,
          "column": 22
        },
        "end": {
          "line": 1,
          "column": 23
        }
      }
    },
    {
      "type": {
        "label": "name",
        "beforeExpr": false,
        "startsExpr": true,
        "rightAssociative": false,
        "isLoop": false,
        "isAssign": false,
        "prefix": false,
        "postfix": false,
        "binop": null
      },
      "value": "create",
      "start": 26,
      "end": 32,
      "loc": {
        "start": {
          "line": 2,
          "column": 2
        },
        "end": {
          "line": 2,
          "column": 8
        }
      }
    },
    {
      "type": {
        "label": "(",
        "beforeExpr": true,
        "startsExpr": true,
        "rightAssociative": false,
        "isLoop": false,
        "isAssign": false,
        "prefix": false,
        "postfix": false,
        "binop": null
      },
      "start": 33,
      "end": 34,
      "loc": {
        "start": {
          "line": 2,
          "column": 9
        },
        "end": {
          "line": 2,
          "column": 10
        }
      }
    },
    {
      "type": {
        "label": "name",
        "beforeExpr": false,
        "startsExpr": true,
        "rightAssociative": false,
        "isLoop": false,
        "isAssign": false,
        "prefix": false,
        "postfix": false,
        "binop": null
      },
      "value": "runtimeOptions",
      "start": 34,
      "end": 48,
      "loc": {
        "start": {
          "line": 2,
          "column": 10
        },
        "end": {
          "line": 2,
          "column": 24
        }
      }
    },
    {
      "type": {
        "label": ")",
        "beforeExpr": false,
        "startsExpr": false,
        "rightAssociative": false,
        "isLoop": false,
        "isAssign": false,
        "prefix": false,
        "postfix": false,
        "binop": null
      },
      "start": 48,
      "end": 49,
      "loc": {
        "start": {
          "line": 2,
          "column": 24
        },
        "end": {
          "line": 2,
          "column": 25
        }
      }
    },
    {
      "type": {
        "label": "{",
        "beforeExpr": true,
        "startsExpr": true,
        "rightAssociative": false,
        "isLoop": false,
        "isAssign": false,
        "prefix": false,
        "postfix": false,
        "binop": null
      },
      "start": 50,
      "end": 51,
      "loc": {
        "start": {
          "line": 2,
          "column": 26
        },
        "end": {
          "line": 2,
          "column": 27
        }
      }
    },
    {
      "type": {
        "label": "if",
        "keyword": "if",
        "beforeExpr": false,
        "startsExpr": false,
        "rightAssociative": false,
        "isLoop": false,
        "isAssign": false,
        "prefix": false,
        "postfix": false,
        "binop": null,
        "updateContext": null
      },
      "value": "if",
      "start": 56,
      "end": 58,
      "loc": {
        "start": {
          "line": 3,
          "column": 4
        },
        "end": {
          "line": 3,
          "column": 6
        }
      }
    },
    {
      "type": {
        "label": "(",
        "beforeExpr": true,
        "startsExpr": true,
        "rightAssociative": false,
        "isLoop": false,
        "isAssign": false,
        "prefix": false,
        "postfix": false,
        "binop": null
      },
      "start": 59,
      "end": 60,
      "loc": {
        "start": {
          "line": 3,
          "column": 7
        },
        "end": {
          "line": 3,
          "column": 8
        }
      }
    },
    {
      "type": {
        "label": "prefix",
        "beforeExpr": true,
        "startsExpr": true,
        "rightAssociative": false,
        "isLoop": false,
        "isAssign": false,
        "prefix": true,
        "postfix": false,
        "binop": null,
        "updateContext": null
      },
      "value": "!",
      "start": 60,
      "end": 61,
      "loc": {
        "start": {
          "line": 3,
          "column": 8
        },
        "end": {
          "line": 3,
          "column": 9
        }
      }
    },
    {
      "type": {
        "label": "name",
        "beforeExpr": false,
        "startsExpr": true,
        "rightAssociative": false,
        "isLoop": false,
        "isAssign": false,
        "prefix": false,
        "postfix": false,
        "binop": null
      },
      "value": "runtimeOptions",
      "start": 61,
      "end": 75,
      "loc": {
        "start": {
          "line": 3,
          "column": 9
        },
        "end": {
          "line": 3,
          "column": 23
        }
      }
    },
    {
      "type": {
        "label": ".",
        "beforeExpr": false,
        "startsExpr": false,
        "rightAssociative": false,
        "isLoop": false,
        "isAssign": false,
        "prefix": false,
        "postfix": false,
        "binop": null,
        "updateContext": null
      },
      "start": 75,
      "end": 76,
      "loc": {
        "start": {
          "line": 3,
          "column": 23
        },
        "end": {
          "line": 3,
          "column": 24
        }
      }
    },
    {
      "type": {
        "label": "name",
        "beforeExpr": false,
        "startsExpr": true,
        "rightAssociative": false,
        "isLoop": false,
        "isAssign": false,
        "prefix": false,
        "postfix": false,
        "binop": null
      },
      "value": "useAudio",
      "start": 76,
      "end": 84,
      "loc": {
        "start": {
          "line": 3,
          "column": 24
        },
        "end": {
          "line": 3,
          "column": 32
        }
      }
    },
    {
      "type": {
        "label": ")",
        "beforeExpr": false,
        "startsExpr": false,
        "rightAssociative": false,
        "isLoop": false,
        "isAssign": false,
        "prefix": false,
        "postfix": false,
        "binop": null
      },
      "start": 84,
      "end": 85,
      "loc": {
        "start": {
          "line": 3,
          "column": 32
        },
        "end": {
          "line": 3,
          "column": 33
        }
      }
    },
    {
      "type": {
        "label": "{",
        "beforeExpr": true,
        "startsExpr": true,
        "rightAssociative": false,
        "isLoop": false,
        "isAssign": false,
        "prefix": false,
        "postfix": false,
        "binop": null
      },
      "start": 86,
      "end": 87,
      "loc": {
        "start": {
          "line": 3,
          "column": 34
        },
        "end": {
          "line": 3,
          "column": 35
        }
      }
    },
    {
      "type": {
        "label": "return",
        "keyword": "return",
        "beforeExpr": true,
        "startsExpr": false,
        "rightAssociative": false,
        "isLoop": false,
        "isAssign": false,
        "prefix": false,
        "postfix": false,
        "binop": null,
        "updateContext": null
      },
      "value": "return",
      "start": 94,
      "end": 100,
      "loc": {
        "start": {
          "line": 4,
          "column": 6
        },
        "end": {
          "line": 4,
          "column": 12
        }
      }
    },
    {
      "type": {
        "label": "name",
        "beforeExpr": false,
        "startsExpr": true,
        "rightAssociative": false,
        "isLoop": false,
        "isAssign": false,
        "prefix": false,
        "postfix": false,
        "binop": null
      },
      "value": "undefined",
      "start": 101,
      "end": 110,
      "loc": {
        "start": {
          "line": 4,
          "column": 13
        },
        "end": {
          "line": 4,
          "column": 22
        }
      }
    },
    {
      "type": {
        "label": "}",
        "beforeExpr": false,
        "startsExpr": false,
        "rightAssociative": false,
        "isLoop": false,
        "isAssign": false,
        "prefix": false,
        "postfix": false,
        "binop": null
      },
      "start": 115,
      "end": 116,
      "loc": {
        "start": {
          "line": 5,
          "column": 4
        },
        "end": {
          "line": 5,
          "column": 5
        }
      }
    },
    {
      "type": {
        "label": "const",
        "keyword": "const",
        "beforeExpr": false,
        "startsExpr": false,
        "rightAssociative": false,
        "isLoop": false,
        "isAssign": false,
        "prefix": false,
        "postfix": false,
        "binop": null,
        "updateContext": null
      },
      "value": "const",
      "start": 122,
      "end": 127,
      "loc": {
        "start": {
          "line": 7,
          "column": 4
        },
        "end": {
          "line": 7,
          "column": 9
        }
      }
    },
    {
      "type": {
        "label": "name",
        "beforeExpr": false,
        "startsExpr": true,
        "rightAssociative": false,
        "isLoop": false,
        "isAssign": false,
        "prefix": false,
        "postfix": false,
        "binop": null
      },
      "value": "audio",
      "start": 128,
      "end": 133,
      "loc": {
        "start": {
          "line": 7,
          "column": 10
        },
        "end": {
          "line": 7,
          "column": 15
        }
      }
    },
    {
      "type": {
        "label": "=",
        "beforeExpr": true,
        "startsExpr": false,
        "rightAssociative": false,
        "isLoop": false,
        "isAssign": true,
        "prefix": false,
        "postfix": false,
        "binop": null,
        "updateContext": null
      },
      "value": "=",
      "start": 134,
      "end": 135,
      "loc": {
        "start": {
          "line": 7,
          "column": 16
        },
        "end": {
          "line": 7,
          "column": 17
        }
      }
    },
    {
      "type": {
        "label": "{",
        "beforeExpr": true,
        "startsExpr": true,
        "rightAssociative": false,
        "isLoop": false,
        "isAssign": false,
        "prefix": false,
        "postfix": false,
        "binop": null
      },
      "start": 136,
      "end": 137,
      "loc": {
        "start": {
          "line": 7,
          "column": 18
        },
        "end": {
          "line": 7,
          "column": 19
        }
      }
    },
    {
      "type": {
        "label": "name",
        "beforeExpr": false,
        "startsExpr": true,
        "rightAssociative": false,
        "isLoop": false,
        "isAssign": false,
        "prefix": false,
        "postfix": false,
        "binop": null
      },
      "value": "error",
      "start": 144,
      "end": 149,
      "loc": {
        "start": {
          "line": 8,
          "column": 6
        },
        "end": {
          "line": 8,
          "column": 11
        }
      }
    },
    {
      "type": {
        "label": ":",
        "beforeExpr": true,
        "startsExpr": false,
        "rightAssociative": false,
        "isLoop": false,
        "isAssign": false,
        "prefix": false,
        "postfix": false,
        "binop": null,
        "updateContext": null
      },
      "start": 149,
      "end": 150,
      "loc": {
        "start": {
          "line": 8,
          "column": 11
        },
        "end": {
          "line": 8,
          "column": 12
        }
      }
    },
    {
      "type": {
        "label": "string",
        "beforeExpr": false,
        "startsExpr": true,
        "rightAssociative": false,
        "isLoop": false,
        "isAssign": false,
        "prefix": false,
        "postfix": false,
        "binop": null,
        "updateContext": null
      },
      "value": "Sorry, the Audio Manager is not yet implemented! set useAudio runtime option to false!",
      "start": 151,
      "end": 239,
      "loc": {
        "start": {
          "line": 8,
          "column": 13
        },
        "end": {
          "line": 8,
          "column": 101
        }
      }
    },
    {
      "type": {
        "label": "}",
        "beforeExpr": false,
        "startsExpr": false,
        "rightAssociative": false,
        "isLoop": false,
        "isAssign": false,
        "prefix": false,
        "postfix": false,
        "binop": null
      },
      "start": 244,
      "end": 245,
      "loc": {
        "start": {
          "line": 9,
          "column": 4
        },
        "end": {
          "line": 9,
          "column": 5
        }
      }
    },
    {
      "type": {
        "label": "return",
        "keyword": "return",
        "beforeExpr": true,
        "startsExpr": false,
        "rightAssociative": false,
        "isLoop": false,
        "isAssign": false,
        "prefix": false,
        "postfix": false,
        "binop": null,
        "updateContext": null
      },
      "value": "return",
      "start": 251,
      "end": 257,
      "loc": {
        "start": {
          "line": 11,
          "column": 4
        },
        "end": {
          "line": 11,
          "column": 10
        }
      }
    },
    {
      "type": {
        "label": "name",
        "beforeExpr": false,
        "startsExpr": true,
        "rightAssociative": false,
        "isLoop": false,
        "isAssign": false,
        "prefix": false,
        "postfix": false,
        "binop": null
      },
      "value": "audio",
      "start": 258,
      "end": 263,
      "loc": {
        "start": {
          "line": 11,
          "column": 11
        },
        "end": {
          "line": 11,
          "column": 16
        }
      }
    },
    {
      "type": {
        "label": "}",
        "beforeExpr": false,
        "startsExpr": false,
        "rightAssociative": false,
        "isLoop": false,
        "isAssign": false,
        "prefix": false,
        "postfix": false,
        "binop": null
      },
      "start": 266,
      "end": 267,
      "loc": {
        "start": {
          "line": 12,
          "column": 2
        },
        "end": {
          "line": 12,
          "column": 3
        }
      }
    },
    {
      "type": {
        "label": "}",
        "beforeExpr": false,
        "startsExpr": false,
        "rightAssociative": false,
        "isLoop": false,
        "isAssign": false,
        "prefix": false,
        "postfix": false,
        "binop": null
      },
      "start": 268,
      "end": 269,
      "loc": {
        "start": {
          "line": 13,
          "column": 0
        },
        "end": {
          "line": 13,
          "column": 1
        }
      }
    },
    {
      "type": {
        "label": "export",
        "keyword": "export",
        "beforeExpr": false,
        "startsExpr": false,
        "rightAssociative": false,
        "isLoop": false,
        "isAssign": false,
        "prefix": false,
        "postfix": false,
        "binop": null,
        "updateContext": null
      },
      "value": "export",
      "start": 271,
      "end": 277,
      "loc": {
        "start": {
          "line": 15,
          "column": 0
        },
        "end": {
          "line": 15,
          "column": 6
        }
      }
    },
    {
      "type": {
        "label": "default",
        "keyword": "default",
        "beforeExpr": true,
        "startsExpr": false,
        "rightAssociative": false,
        "isLoop": false,
        "isAssign": false,
        "prefix": false,
        "postfix": false,
        "binop": null,
        "updateContext": null
      },
      "value": "default",
      "start": 278,
      "end": 285,
      "loc": {
        "start": {
          "line": 15,
          "column": 7
        },
        "end": {
          "line": 15,
          "column": 14
        }
      }
    },
    {
      "type": {
        "label": "name",
        "beforeExpr": false,
        "startsExpr": true,
        "rightAssociative": false,
        "isLoop": false,
        "isAssign": false,
        "prefix": false,
        "postfix": false,
        "binop": null
      },
      "value": "unimplemented",
      "start": 286,
      "end": 299,
      "loc": {
        "start": {
          "line": 15,
          "column": 15
        },
        "end": {
          "line": 15,
          "column": 28
        }
      }
    },
    {
      "type": {
        "label": "eof",
        "beforeExpr": false,
        "startsExpr": false,
        "rightAssociative": false,
        "isLoop": false,
        "isAssign": false,
        "prefix": false,
        "postfix": false,
        "binop": null,
        "updateContext": null
      },
      "start": 300,
      "end": 300,
      "loc": {
        "start": {
          "line": 16,
          "column": 0
        },
        "end": {
          "line": 16,
          "column": 0
        }
      }
    }
  ]
}